cprl_functions/__init__.py
cprl_functions/defined_functions.py
cprl_functions/state_capture.py
cprl_functions/text_printing.py
cprl_functions-0.0.7.dist-info/METADATA
cprl_functions-0.0.7.dist-info/WHEEL
cprl_functions-0.0.7.dist-info/top_level.txt
cprl_functions-0.0.7.dist-info/RECORD
